fivetran_provider_async/__init__.py
fivetran_provider_async/hooks.py
fivetran_provider_async/operators.py
fivetran_provider_async/py.typed
fivetran_provider_async/sensors.py
fivetran_provider_async/triggers.py
fivetran_provider_async/utils/__init__.py
fivetran_provider_async/utils/operator_utils.py
airflow_provider_fivetran_async-2.2.0.dist-info/METADATA
airflow_provider_fivetran_async-2.2.0.dist-info/WHEEL
airflow_provider_fivetran_async-2.2.0.dist-info/entry_points.txt
airflow_provider_fivetran_async-2.2.0.dist-info/licenses/LICENSE
airflow_provider_fivetran_async-2.2.0.dist-info/RECORD
