Metadata-Version: 2.4
Name: airflow-provider-fivetran-async
Version: 2.2.0
Summary: A Fivetran async provider for Apache Airflow
Project-URL: Source, https://github.com/astronomer/airflow-provider-fivetran-async
Author-email: Astronomer & Fivetran <humans@astronomer.io>
License-Expression: Apache-2.0
License-File: LICENSE
Keywords: airflow,apache-airflow,astronomer,dag,provider
Classifier: Development Status :: 5 - Production/Stable
Classifier: Framework :: Apache Airflow
Classifier: Intended Audience :: Developers
Classifier: License :: OSI Approved :: Apache Software License
Classifier: Programming Language :: Python :: 3
Classifier: Programming Language :: Python :: 3 :: Only
Classifier: Programming Language :: Python :: 3.9
Classifier: Programming Language :: Python :: 3.10
Classifier: Programming Language :: Python :: 3.11
Classifier: Programming Language :: Python :: 3.12
Classifier: Programming Language :: Python :: Implementation :: CPython
Classifier: Programming Language :: Python :: Implementation :: PyPy
Classifier: Topic :: Database
Classifier: Typing :: Typed
Requires-Python: >=3.9
Requires-Dist: aiohttp
Requires-Dist: apache-airflow>=2.4.0
Requires-Dist: asgiref
Requires-Dist: openlineage-airflow>=0.19.2
Requires-Dist: requests
Provides-Extra: tests
Requires-Dist: mypy; extra == 'tests'
Requires-Dist: parameterized; extra == 'tests'
Requires-Dist: pre-commit; extra == 'tests'
Requires-Dist: pytest; extra == 'tests'
Requires-Dist: pytest-asyncio; extra == 'tests'
Requires-Dist: pytest-cov; extra == 'tests'
Requires-Dist: requests-mock; extra == 'tests'
Requires-Dist: types-requests; extra == 'tests'
